goa_loader/__init__.py
goa_loader/download_data.py
goa_loader/load.py
goa_loader/path.py
goa_loader/util.py
goa_loader-0.1.2.dist-info/LICENSE
goa_loader-0.1.2.dist-info/METADATA
goa_loader-0.1.2.dist-info/WHEEL
goa_loader-0.1.2.dist-info/top_level.txt
goa_loader-0.1.2.dist-info/RECORD
