Metadata-Version: 2.1
Name: goa-loader
Version: 0.1.2
Summary: UNKNOWN
Home-page: https://github.com/lukewood/goa-loader
Author: Luke Wood
Author-email: lukewoodcs@gmail.com
License: Apache License 2.0
Platform: UNKNOWN
Classifier: Development Status :: 5 - Production/Stable
Classifier: Environment :: Console
Classifier: License :: OSI Approved :: Apache Software License
Classifier: Intended Audience :: Science/Research
Classifier: Programming Language :: Python :: 3
Classifier: Topic :: Scientific/Engineering :: Artificial Intelligence
License-File: LICENSE
Requires-Dist: termcolor
Requires-Dist: joblib
Requires-Dist: pandas
Requires-Dist: tqdm
Requires-Dist: tensorflow
Requires-Dist: keras-cv
Provides-Extra: dev
Requires-Dist: flake8 ; extra == 'dev'
Requires-Dist: pytest ; extra == 'dev'
Requires-Dist: pytype ; extra == 'dev'
Requires-Dist: setuptools ; extra == 'dev'
Requires-Dist: twine ; extra == 'dev'
Requires-Dist: wheel ; extra == 'dev'
